{"OPrlflbOTyv1vecodB/7Xw==":"posts%20agosto%20-%20organizet.gif","MHnozHoZ/KyCJEXS404C4Q==":"mbr-696x464.jpg","1ZOAgKA2jqhpSZ86Msz4iQ==":"mbr-1-696x464.jpg","2ZaDd9JfmXAFepTiAqnIBw==":"inda_qamar_15(0)-1400x1000.jpg","yktGqOxlQjTzO3S06WZlzQ==":"axolight_u-light_suspension_90_rust_brown_set-2-1500x1055.jpeg","RUUuhKvsViAdCkwwICB4VQ==":"h-374-compasso-pag-7-b-2000x1913.jpg","hfJh7mhzfFAPSr9ks0gKAQ==":"catalano-250x210.jpg","opxYRU1X5Y2/FknrNY729g==":"tarimatec-250x210.jpg","OLqmgX03UEUtqfcXy2o/1w==":"admonter-250x210.jpg","24ZiVsx1D7SeY3V8SuJjKw==":"inda-1-250x210.jpg","pWqUb2PzbW7I1C/i8eCV1Q==":"finefloors-250x210.jpg","Gg9KukzwK1R1W1QGXLElyQ==":"valli&valli-250x210.jpg","C857zjilNFuJBLy3og9m+A==":"mysecret-inda-particolare-2-1024x683.png","xb67ci8/34pvXbY7e09GuQ==":"fusital-250x210.jpg","you+WqKSnXlC1kL8Y/b79w==":"axolight-250x210.jpg","WfTPp4IEXcf4/pcRY65vug==":"mbr-1920x1280.jpg","1N9bAXbB8PIDFWAB6/9Mgw==":"a1-centro-de-disen%CC%83o-924x676.jpg","v8CZkrRRAws36GcowsQ6SQ==":"s5a9334-scaled-2000x1334.jpg","cL1X9zcFl9dnJBLxnwLgbQ==":"product1.jpg","kaAoq6RQJm6Z1/ZqvRtQtA==":"background2.jpg","oJQdtKQ2bdLajZtjcIzUUA==":"background3.jpg","dHZ2uR8IYJk3zrwzKqdCww==":"elements_foto2-1536x1120.jpg","A7/SERDztQ6WDNf149rlwQ==":"sofia-cabassa-1-924x676.jpg","cpD6OacVP5FNIfJDxww2qg==":"bot_gessi-575x383.jpg","ipqCOydCjJTqS3fqoZHdrQ==":"bot_catalano-575x383.jpg","L6CzGpADrC4TiMk7CyY4fw==":"a1-centro-de-disen%CC%83o-924x676.jpg","QOnKIkERVuOn848olDy1KQ==":"67260034_2874880806070731_7380967676895559680_n-960x960.jpg","5oxGSBdOb5s3e3IjvVVemg==":"67244259_2874881052737373_523604771634937856_o-960x960.jpg","CMmEIgCWedNe1Vxo38iJ6w==":"67084912_2874881009404044_8028445773567885312_o-960x960.jpg","R78CHqME+sZKjZ9pwJmg0g==":"bot_inda%20copy-575x383.jpg","k8UWDpmoCuSogjC42PeqHw==":"bot_ess-575x383.jpg","xOUVXbFt12tpMC8o7fKo8w==":"bot_valli&valli-575x383.jpg","sgVTVItoa33Ov7rTexMQ8A==":"bot_fusital-575x383.jpg","iTIjalJpgNiXrQ9ZsUz6tg==":"bot_tarimatec-575x383.jpg","hmKrKpHBvS5kFZwnX8jK+A==":"bot_admonter-575x383.jpg","xDpEgqs3G4ifGd8ZiDwEtQ==":"bot_purnatur-1-575x383.jpg","qRtKh782LCPBIdtVodaF6g==":"bot_finefloors-575x383.jpg","NS40rW6h68EWjcjOdBKW1g==":"bot_axolight-1-575x383.jpg","ErAEW+h23Rnj1KqtFijEEg==":"bot_santa_cole-575x383.jpg","6XiuaBgsaaTDI0uyxp5LzQ==":"pedrera_read_the_objects_santacole-2000x1047.jpg","E4LIMBIQ4/hGkOIJvVzN7w==":"beforeandafter-1-960x1920.jpg","aVABeb5b1SPrqKkbFPvl7w==":"gessi-1-250x210.jpg","FzUCYMjxO8moti7DnDGmxw==":"easy-drain-250x210.jpg","+0dV3TFrsybfwPXjPB3htg==":"purnatur-250x210.jpg","SHlHLs5PQDkVOI6J5BJ5dQ==":"santa&cole-250x210.jpg","8kRrqSQUZqst6gbbU/SY7g==":"logo-a1.svg","lGCao9DH920ce3Zm+bXv4g==":"bathroom-easydrain-1800x1500.jpg","n8qOkF16WMwIF6y9lOv3CQ==":"inciso_gessi-1500x892.jpg","FwxiBP7v+dF1EFxGGml/Jg==":"baf-b-de-visitas-960x1920.jpg","1ZwZAq9zE4VIFU1gaDYGYQ==":"display-casa-studio-ambiente-1-1080x1080.jpg","oYtUr2PcrhK/SJBDqNt+AQ==":"display-casa-studio-ambiente-2-1080x1080.jpg","gvuUgUipVO39IIQp9uEVBw==":"baf-pergola-ingreso-960x1920.jpg","DQp4Iuyd1nqUhynTcLWdig==":"infasa-3-1080x1080.jpg","uylKl59OYa2AKEe6avXrNg==":"infasa-2-1080x1080.jpg","ElF3SlZqZNxCJeL28tVvew==":"infasa-4-1080x1080.jpg","YTpN4kURfotO+jHV27VRcA==":"hdg-2-1080x1080.jpg","ZebnuTXamnAhOlhyUb0h4A==":"hdg-3-1080x1080.jpg","NgWaD/yR0oEtv3LuM0ewuw==":"zero-park-6-1080x1080.jpg","32zACRKNdv70Y6dT5Q5B9g==":"zero-park-1-1080x1080.jpg","CeK8IR3HfDISGRUisgufQg==":"zero-park-2-1080x1080.jpg","AJNAPdrZRIyJ/N42LibcbQ==":"zero-park-3-1080x1080.jpg","a36bZlducuB46VPwXd3uyQ==":"zero-park-4-1080x1080.jpg","Kob0dIpYj0Q6856PW1zujA==":"zero-park-5-1080x1080.jpg","dW4Rp76HFo4e9dicFXltHg==":"baf-pergola-r-960x1920.jpg","aRM4w8a7VgGMsGAvhwfgqA==":"centeno-1080x1080.jpg","ZMdXIocwXcebjBybglrNiw==":"baf-b-960x1920.jpg","pYIO166xvuCrwefNrK09iw==":"baf-b-principal-r2-960x1920.jpg","BUR40vogMx5Kuq5y+CgxTw==":"baf-b-principal-r3-960x1920.jpg","Dd7uGxFIGAmJRm8W4YKk8Q==":"baf-b-principal-c2-960x1920.jpg","JbioJo9nXi0xw4sDW3Fuhg==":"imagen-sala-a1-1800x1350.jpg"}